Metadata-Version: 2.4
Name: cocotb-vivado
Version: 0.0.5
Summary: Limited cocotb/Python interface for Xilinx Vivado Simulator
Home-page: https://github.com/themperek/cocotb-vivado
Author: Tomasz Hemperek
Author-email: themperek@gmail.com
License: Apache 2.0
Keywords: SystemVerilog,Verilog,RTL,cocotb,Python,Vivado,Xilinx,xsim,xsi
Platform: any
Classifier: Programming Language :: Python :: 3
Classifier: License :: OSI Approved :: BSD License
Classifier: Topic :: Scientific/Engineering :: Electronic Design Automation (EDA)
Classifier: Framework :: cocotb
License-File: LICENSE
Requires-Dist: cocotb<2.0,>=1.8
Dynamic: author
Dynamic: author-email
Dynamic: classifier
Dynamic: description
Dynamic: description-content-type
Dynamic: home-page
Dynamic: keywords
Dynamic: license
Dynamic: license-file
Dynamic: platform
Dynamic: requires-dist
Dynamic: summary
